{
  "meno": "Sticky slime",
  "obrazok": "slime",
  "levelOd": 1,
  "levelDo": 3,
  "hpOd": 15,
  "hpDo": 20,
  "mpOd": 2,
  "mpDo": 6,
  "silaOd": 1,
  "silaDo": 4,
  "intelektOd": 1,
  "intelektDo": 1,
  "redukciaMin": 10,
  "redukciaMax": 20,
  "uhybMin": 10,
  "uhybMax": 20,

  "akcie": {
    "1": {
      "typ": "AkciaDmg",
      "meno": "Accidic touch",
      "obrazok": "attack",
      "rychlostCastenia": 2000,
      "cooldown": 500,
      "trvanie": 0,
      "popis": "",
      "stat": "fyzicka",
      "mana": 0,
      "zakladnaHodnota": 1.0
    },
    "2": {
      "typ": "AkciaPridanieEfektu",
      "meno": "Aciddic spittle",
      "obrazok": "attack",
      "rychlostCastenia": 2000,
      "cooldown": 10000,
      "trvanie": 4000,
      "popis": "",
      "stat": "fyzicka",
      "mana": 2,
      "zakladnaHodnota": 1,

      "efekt": {
        "druh": "upravStat",
        "obrazok": "shout",
        "stat": "sila",
        "hodnota": -1,
        "naSeba": false
      }

    }
  },

  "questDrop": {

  }

}